ctsh/__init__.py
ctsh/__main__.py
ctsh/completer.py
ctsh/context.py
ctsh/fmt.py
ctsh/main.py
ctsh/parser.py
ctsh/utils.py
ctsh/version.py
ctsh/commands/__init__.py
ctsh/commands/base.py
carrot_shell-0.2.8.dist-info/LICENSE
carrot_shell-0.2.8.dist-info/METADATA
carrot_shell-0.2.8.dist-info/WHEEL
carrot_shell-0.2.8.dist-info/entry_points.txt
carrot_shell-0.2.8.dist-info/top_level.txt
carrot_shell-0.2.8.dist-info/RECORD
