Metadata-Version: 2.1
Name: carrot-shell
Version: 0.2.8
Summary: Carrot shell🥕 is the best shell in python, for developers.
Home-page: https://github.com/blueloveTH/carrot-shell
Author: blueloveTH
Author-email: blueloveth@foxmail.com
Classifier: Programming Language :: Python :: 3
Classifier: License :: OSI Approved :: MIT License
Classifier: Operating System :: OS Independent
Requires-Python: >=3.8
License-File: LICENSE
